{
  "title_clean": "Practice makes perfect.*",
  "description_short": "Bhante Bodhidhamma explores the essential role of dedicated practice in spiritual development, comparing Buddhist training to athletic discipline.",
  "description_long": "Bhante Bodhidhamma draws compelling parallels between spiritual practice and athletic training, emphasizing that meaningful repetition requires clear purpose and dedication. The essay explores how the Buddha's teachings provide both technique (vipassanā meditation) and guidance for maintaining Right Awareness (sammā sati) in daily life, grounded in ethical conduct and mettā (loving-kindness).\n\nThe author explains that sitting meditation practice involves repeatedly returning attention to the present moment and the breath, allowing natural insights to arise into the three characteristics of existence: dukkha (unsatisfactoriness), anicca (impermanence), and anattā (not-self). These insights emerge not as dramatic revelations but as moments of recognition that deepen understanding gradually.\n\nBhante Bodhidhamma emphasizes that daily life itself becomes the practice when Right Awareness is combined with ethical behavior. Even routine activities like morning ablutions or eating can become opportunities for 'this-moment-attention' practiced with a wholesome heart. The essay concludes with the crucial point that spiritual aspiration without dedicated practice leads only to fantasy and disappointment, reminding practitioners that even the Buddha achieved awakening through committed practice, not aspiration alone.\n\n(This description was generated automatically, inaccuracies may happen in the process.)",
  "keywords": [
    "vipassanā",
    "sammā sati",
    "Right Awareness",
    "practice",
    "meditation",
    "mettā",
    "daily life practice",
    "three characteristics",
    "dukkha",
    "anicca",
    "anattā",
    "ethical conduct",
    "dedication",
    "awakening",
    "mindfulness"
  ],
  "difficulty": "introductory"
}