{
  "title_clean": "Feeling (Vedanā)",
  "description_short": "Bhante Bodhidhamma explores vedanā, the second aggregate, examining how feelings arise from sense contact and condition our experience of happiness and suffering.",
  "description_long": "In this exploration of vedanā (feeling), Bhante Bodhidhamma examines the second of the five aggregates, tracing how feelings arise from the initial point of contact (phassa) at the sense bases. Drawing extensively from the Pañcakaṅga Sutta, he unfolds the Buddha's detailed classification of feelings—from the basic two-fold division of pleasant and unpleasant, through the traditional three-fold classification, up to 108 different types of feelings when categorized by sense base, time, and spiritual quality.\n\nThe talk addresses a fundamental insight: what we truly seek in life is not external objects but the inner feeling of happiness itself. Bhante explores how this understanding transforms our relationship to experience, distinguishing between worldly feelings based on sensual pleasure and renunciation feelings based on seeing impermanence. He clarifies common misconceptions about karma, explaining that not all feelings arise from past actions—many result from present conditions like weather, diet, or current mental states.\n\nThe discussion extends to the refined feelings experienced in jhāna states and the ultimate cessation of feeling and perception. Throughout, Bhante emphasizes the practical importance of developing awareness of vedanā in meditation, as feelings form the bridge between sensory contact and the mental proliferation that leads to suffering. This detailed examination provides essential groundwork for understanding how feelings condition our entire experience of existence.\n\n(This description was generated automatically, inaccuracies may happen in the process.)",
  "keywords": [
    "vedanā",
    "feeling",
    "aggregates",
    "khandha",
    "phassa",
    "contact",
    "sense bases",
    "Pañcakaṅga Sutta",
    "pleasant",
    "unpleasant",
    "neutral",
    "jhāna",
    "karma",
    "worldly",
    "renunciation",
    "equanimity",
    "happiness",
    "dukkha",
    "sukha"
  ],
  "difficulty": "intermediate"
}