{
  "title_clean": "Les Facteurs de Libération",
  "description_short": "Bhante Bodhidhamma explore l'union des cinq facultés spirituelles et des sept facteurs d'éveil, montrant comment l'attention juste (sammā sati) les développe naturellement.",
  "description_long": "Dans cette conférence donnée à Lausanne, Bhante Bodhidhamma présente une synthèse profonde des aspects subtils de la méditation vipassanā en unissant les cinq facultés spirituelles (indriya) et les sept facteurs d'éveil (bojjhaṅga). Il explore comment saddhā (confiance) s'équilibre avec paññā (sagesse), soulignant l'importance de développer à la fois l'aspect intellectuel et dévotionnel de la pratique. La conférence examine en détail l'équilibre délicat entre l'effort et la concentration (samādhi), ainsi qu'entre le calme (passaddhi) et l'intérêt spirituel (pīti).\n\nBhante explique comment l'équanimité (upekkhā) permet l'investigation directe du Dharma, particulièrement les trois caractéristiques universelles : anicca (impermanence), dukkha (insatisfaction) et anattā (non-soi). Il met l'accent sur la nécessité de maintenir une position de « ne pas savoir » pour éviter que la confiance ne se rigidifie en croyance aveugle.\n\nLa conférence culmine avec l'enseignement fondamental que lorsque sammā sati (l'attention juste) est établie - selon la méthode du Satipaṭṭhāna Sutta - tous ces facteurs spirituels surgissent naturellement pour la soutenir, rendant la pratique à la fois simple et profonde.\n\n(This description was generated automatically, inaccuracies may happen in the process.)",
  "keywords": [
    "facultés spirituelles",
    "facteurs d'éveil",
    "bojjhaṅga",
    "indriya",
    "sammā sati",
    "saddhā",
    "paññā",
    "samādhi",
    "équanimité",
    "investigation du Dharma",
    "trois caractéristiques",
    "anicca",
    "dukkha",
    "anattā",
    "vipassanā",
    "attention juste",
    "Satipaṭṭhāna"
  ],
  "difficulty": "intermediate"
}