{
  "title_clean": "Paṭicca Samuppāda - L'Origination Interdépendante (Belgique Jan 2006)",
  "description_short": "Bhante Bodhidhamma explore les douze maillons du paṭicca samuppāda, révélant comment l'ignorance génère la souffrance et comment la sagesse libère.",
  "description_long": "Dans cette conférence donnée en français, Bhante Bodhidhamma présente un enseignement approfondi sur le paṭicca samuppāda (origination interdépendante), l'un des piliers fondamentaux de la psychologie bouddhiste. Il détaille les douze maillons de cette chaîne causale : de l'avijjā (ignorance) aux saṅkhāra (formations mentales), jusqu'à la conscience, nāma-rūpa (nom-et-forme), les six bases sensorielles, le contact (phassa), les sensations (vedanā), le désir (taṇhā), l'attachement (upādāna), le devenir (bhava), la naissance et la mort.\n\nL'enseignement révèle comment chaque maillon conditionne le suivant, créant un cycle de dukkha (souffrance). Bhante explique particulièrement le rôle crucial du moment entre vedanā et taṇhā - où la sagesse peut intervenir pour briser la chaîne. Il illustre comment la méditation vipassanā nous permet d'observer ce processus avec clarté, nous positionnant au 'sommet du cône' comme témoin objectif plutôt que d'être pris dans le cercle du désir.\n\nCette exploration psychologique profonde montre comment l'illusion du 'moi' génère toutes nos réactions négatives, et comment la compréhension directe de anattā (non-soi) peut libérer complètement de ce conditionnement, restaurant notre innocence et pureté originelles.\n\n(This description was generated automatically, inaccuracies may happen in the process.)",
  "keywords": [
    "paṭicca samuppāda",
    "origination interdépendante",
    "avijjā",
    "ignorance",
    "saṅkhāra",
    "vedanā",
    "taṇhā",
    "upādāna",
    "dukkha",
    "vipassanā",
    "anattā",
    "non-soi",
    "conditionnement",
    "sagesse",
    "libération"
  ],
  "difficulty": "advanced"
}