{
  "title_clean": "The Perfections (Pāramī)",
  "description_short": "Bhante Bodhidhamma explores the pāramī (perfections) as practical qualities for spiritual development, focusing on generosity (dāna) and renunciation (nekkhamma).",
  "description_long": "In this talk given in Czech, Bhante Bodhidhamma examines the ten pāramī (perfections) as essential qualities for crossing from ordinary consciousness to awakening. He begins by contextualizing karma within the framework of dependent origination, emphasizing that the Buddha taught that both dukkha and its cessation exist within this two-meter-tall body.\n\nThe discussion focuses primarily on two interconnected perfections: generosity (dāna) and renunciation (nekkhamma). Bhante explains that while generosity is the easiest perfection to develop, true dāna requires pure intention without expectation of return. He offers practical guidance on cultivating genuine generosity by examining our motivations and recognizing the subtle ego-driven desires that can corrupt giving.\n\nThe exploration of nekkhamma reveals how renunciation differs from self-mortification. Rather than viewing the body as evil, Buddhist renunciation involves recognizing our attachments by occasionally letting go of things we cling to. This practice reveals the strength of our ulpādāna (clinging) and leads to greater freedom and peace of mind. The talk emphasizes how these perfections work together to develop the wholesome conditioning necessary for spiritual progress.\n\n(This description was generated automatically, inaccuracies may happen in the process.)",
  "keywords": [
    "pāramī",
    "perfections",
    "dāna",
    "generosity",
    "nekkhamma",
    "renunciation",
    "karma",
    "dukkha",
    "dependent origination",
    "ulpādāna",
    "clinging",
    "intention",
    "spiritual development"
  ],
  "difficulty": "intermediate"
}