{
  "title_clean": "The Eight Worldly Conditions",
  "description_short": "Bhante Bodhidhamma explores the aṭṭha loka dhamma — the eight worldly conditions of gain/loss, fame/disrepute, praise/blame, pleasure/pain — and how to develop equanimity toward life's inevitable u...",
  "description_long": "In this profound exploration of the aṭṭha loka dhamma (eight worldly conditions), Bhante Bodhidhamma examines how gain and loss, fame and disrepute, praise and blame, pleasure and pain create mental turbulence when we become obsessed with them. Drawing from the Buddha's teachings, he explains how these conditions arise from our sense of self and how personalizing these experiences — 'it's me that's blamed, it's me that's praised' — creates unnecessary suffering.\n\nThrough practical reflection questions, Bhante guides us to investigate our own relationships with these worldly vicissitudes. He distinguishes between wholesome desires (needing money, friends) and obsessive craving, and between appropriate congratulations and ego-driven attachment to success. The talk emphasizes developing equanimity — that balanced state where we can receive life's experiences without the welcoming and rebelling that keeps us trapped in dukkha.\n\nBhante references the Buddha's description of the arahat who remains 'unshaken by worldly vicissitudes' as one of the greatest blessings. This teaching offers a practical framework for understanding how the less we personalize life's inevitable changes, the more peace and freedom we can experience. Essential listening for anyone seeking to apply Buddhist wisdom to daily life's challenges.\n\n(This description was generated automatically, inaccuracies may happen in the process.)",
  "keywords": [
    "aṭṭha loka dhamma",
    "eight worldly conditions",
    "equanimity",
    "attachment",
    "dukkha",
    "not-self",
    "anattā",
    "arahat",
    "worldly winds",
    "gain and loss",
    "praise and blame",
    "pleasure and pain",
    "craving",
    "personalization",
    "ego",
    "restraint"
  ],
  "difficulty": "intermediate"
}