{
  "title_clean": "The Importance of Tranquillity",
  "description_short": "Bhante Bodhidhamma explores passaddhi, tranquillity as one of the seven factors of awakening, examining its effects on body and mind in meditation and daily life.",
  "description_long": "In this comprehensive teaching, Bhante Bodhidhamma explores passaddhi (tranquillity) as one of the seven bojjhaṅgas (factors of awakening). He examines how calmness affects both body and mind, discussing the physiological benefits including the activation of the parasympathetic nervous system, release of beneficial neurotransmitters like serotonin and endorphins, and reduction of cortisol.\n\nThe talk covers the relationship between physical relaxation and mental states in Buddhist understanding, explaining how tranquillity supports samatha (calming) practices and leads naturally into right concentration (sammā samādhi). Bhante discusses how calmness underlies the four brahmavihāras (divine abidings) - particularly upekkhā (equanimity) - and connects to the deeper states of jhāna.\n\nPractical guidance is offered for cultivating tranquillity in daily life: taking pauses between tasks, mindful breathing before sleep, and making decisions only from calm states. The teaching emphasizes that passaddhi is not merely relaxation but a crucial spiritual quality that enables wisdom, improves relationships, and supports both vipassanā insight and the ultimate peace of nibbāna as described in the Metta Sutta.\n\n(This description was generated automatically, inaccuracies may happen in the process.)",
  "keywords": [
    "passaddhi",
    "tranquillity",
    "bojjhaṅgas",
    "factors of awakening",
    "samatha",
    "concentration",
    "sammā samādhi",
    "brahmavihāras",
    "upekkhā",
    "equanimity",
    "jhāna",
    "nibbāna",
    "Metta Sutta",
    "parasympathetic nervous system",
    "mindfulness",
    "daily practice"
  ],
  "difficulty": "intermediate"
}