{
  "title_clean": "The Five Constant Contemplations",
  "description_short": "Bhante Bodhidhamma explores the Buddha's five regular contemplations on aging, illness, death, separation, and karma from the Aṅguttara Nikāya.",
  "description_long": "In this profound teaching, Bhante Bodhidhamma examines the five themes for regular contemplation outlined by the Buddha in the Aṅguttara Nikāya (AN 5.57). These contemplations address our universal human condition: aging, illness, death, separation from all we hold dear, and our ownership of karma. Rather than morbid reflections, these practices serve to undermine our intoxications with health, youth, and life that lead to unwholesome conduct.\n\nBhante explains how proper contemplation works—not as mere intellectual thinking, but as a heart-practice that allows us to deeply digest difficult truths until resistance dissolves into acceptance. He provides practical phrases and methods for each contemplation, emphasizing how this universal human condition offers strange comfort rather than despair. The teaching includes the Buddha's own verse on how these reflections led to his renunciation and awakening.\n\nThese contemplations directly support the path to liberation by abandoning the fetters and uprooting underlying unwholesome tendencies. The session concludes with guided contemplative phrases for each of the five themes, offering practitioners concrete tools for this transformative practice.\n\n(This description was generated automatically, inaccuracies may happen in the process.)",
  "keywords": [
    "contemplation",
    "death meditation",
    "aging",
    "illness",
    "separation",
    "karma",
    "renunciation",
    "fetters",
    "Aṅguttara Nikāya",
    "liberation",
    "dukkha",
    "anattā",
    "impermanence",
    "heart practice"
  ],
  "difficulty": "intermediate"
}