{
  "title_clean": "Facets of a Love",
  "description_short": "Bhante Bodhidhamma explores the essential qualities that underpin genuine loving relationships, from care and kindness to gratitude and forgiveness.",
  "description_long": "In this heartfelt exploration of love and relationship, Bhante Bodhidhamma moves beyond romantic notions to examine the fundamental qualities that create genuine human connection. Drawing on the Buddha's teachings about spiritual friendship, he identifies care as the foundation of love—recognizing our deep interconnectedness rather than viewing others as competitors in our individualistic society.\n\nThe talk weaves together practical wisdom about expressing affection through kindness, while warning against using or controlling others. Bhante emphasizes two crucial underpinnings of all relationships: gratitude and forgiveness. He shares the story of three Arahats living in harmony by each putting aside their personal preferences for others' benefit, and offers the amusing tale of a journalist applying dolphin training techniques to improve her marriage.\n\nConcluding with the Buddha's teaching to Ānanda that spiritual friendship constitutes the entire spiritual life, Bhante shows how good companionship supports our development of the Noble Eightfold Path. This accessible talk offers invaluable guidance for anyone seeking to cultivate more caring, harmonious relationships—whether intimate partnerships, friendships, or community connections—grounded in Buddhist wisdom about our shared humanity.\n\n(This description was generated automatically, inaccuracies may happen in the process.)",
  "keywords": [
    "love",
    "relationships",
    "mettā",
    "spiritual friendship",
    "kalyāṇamitra",
    "Noble Eightfold Path",
    "interconnectedness",
    "care",
    "kindness",
    "gratitude",
    "forgiveness",
    "Ānanda",
    "arahats",
    "community",
    "harmony"
  ],
  "difficulty": "introductory"
}